hveto/__init__.py
hveto/__main__.py
hveto/_version.py
hveto/config.py
hveto/const.py
hveto/core.py
hveto/html.py
hveto/plot.py
hveto/segments.py
hveto/triggers.py
hveto/utils.py
hveto/cli/__init__.py
hveto/cli/cache_events.py
hveto/cli/trace.py
hveto/cli/tests/__init__.py
hveto/cli/tests/test_trace.py
hveto/tests/__init__.py
hveto/tests/test_core.py
hveto/tests/test_html.py
hveto/tests/test_plot.py
hveto/tests/test_segments.py
hveto/tests/test_triggers.py
hveto/tests/test_utils.py
hveto-2.1.8.dist-info/licenses/LICENSE
hveto-2.1.8.dist-info/METADATA
hveto-2.1.8.dist-info/WHEEL
hveto-2.1.8.dist-info/entry_points.txt
hveto-2.1.8.dist-info/top_level.txt
hveto-2.1.8.dist-info/RECORD
