Metadata-Version: 2.4
Name: hveto
Version: 2.1.8
Summary: A python implementation of the HierarchicalVeto (hveto) algorithm
Author-email: Joshua Smith <joshua.smith@ligo.org>, Duncan Macleod <duncan.macleod@ligo.org>
Maintainer-email: Joe Areeda <joseph.areeda@ligo.org>
Project-URL: Bug Tracker, https://github.com/gwdetchar/hveto/issues
Project-URL: Documentation, https://hveto.readthedocs.io
Project-URL: Source Code, https://github.com/gwdetchar/hveto
Classifier: Development Status :: 5 - Production/Stable
Classifier: Intended Audience :: Developers
Classifier: Intended Audience :: End Users/Desktop
Classifier: Intended Audience :: Science/Research
Classifier: License :: OSI Approved :: GNU General Public License v3 or later (GPLv3+)
Classifier: Natural Language :: English
Classifier: Operating System :: POSIX
Classifier: Operating System :: Unix
Classifier: Operating System :: MacOS
Classifier: Programming Language :: Python
Classifier: Programming Language :: Python :: 3
Classifier: Programming Language :: Python :: 3.10
Classifier: Programming Language :: Python :: 3.11
Classifier: Topic :: Scientific/Engineering
Classifier: Topic :: Scientific/Engineering :: Astronomy
Classifier: Topic :: Scientific/Engineering :: Physics
Requires-Python: >=3.10
License-File: LICENSE
Requires-Dist: gwdetchar>=2.3.2
Requires-Dist: gwpy>=2.0.0
Requires-Dist: gwtrigfind>=0.8.3
Requires-Dist: h5py
Requires-Dist: igwn-ligolw
Requires-Dist: lxml
Requires-Dist: MarkupPy>=1.14
Requires-Dist: matplotlib>=3.1
Requires-Dist: numpy>=1.10
Requires-Dist: scipy
Provides-Extra: test
Requires-Dist: coverage[toml]; extra == "test"
Requires-Dist: pytest>=3.1.0; extra == "test"
Requires-Dist: pytest-cov>=2.4.0; extra == "test"
Provides-Extra: docs
Requires-Dist: numpydoc; extra == "docs"
Requires-Dist: Sphinx; extra == "docs"
Requires-Dist: sphinx_bootstrap_theme; extra == "docs"
Requires-Dist: sphinxcontrib-programoutput; extra == "docs"
Dynamic: license-file
